cloudwanderer/__init__.py
cloudwanderer/base.py
cloudwanderer/cache_helpers.py
cloudwanderer/cloud_wanderer.py
cloudwanderer/cloud_wanderer_resource.py
cloudwanderer/exceptions.py
cloudwanderer/models.py
cloudwanderer/py.typed
cloudwanderer/urn.py
cloudwanderer/utils.py
cloudwanderer/aws_interface/__init__.py
cloudwanderer/aws_interface/aws_services.py
cloudwanderer/aws_interface/boto3_helpers.py
cloudwanderer/aws_interface/boto3_loaders.py
cloudwanderer/aws_interface/exceptions.py
cloudwanderer/aws_interface/interface.py
cloudwanderer/aws_interface/models.py
cloudwanderer/aws_interface/resource_factory.py
cloudwanderer/aws_interface/session.py
cloudwanderer/aws_interface/utils.py
cloudwanderer/aws_interface/resource_definitions/apigateway/2015-07-09/resources-1.json
cloudwanderer/aws_interface/resource_definitions/apigateway/2015-07-09/resources-cw-1.json
cloudwanderer/aws_interface/resource_definitions/autoscaling/2011-01-01/resources-1.json
cloudwanderer/aws_interface/resource_definitions/autoscaling/2011-01-01/resources-cw-1.json
cloudwanderer/aws_interface/resource_definitions/cloudformation/2010-05-15/resources-cw-1.json
cloudwanderer/aws_interface/resource_definitions/cloudwatch/2010-08-01/resources-cw-1.json
cloudwanderer/aws_interface/resource_definitions/dynamodb/2012-08-10/resources-cw-1.json
cloudwanderer/aws_interface/resource_definitions/ec2/2016-11-15/resources-1.json
cloudwanderer/aws_interface/resource_definitions/ec2/2016-11-15/resources-cw-1.json
cloudwanderer/aws_interface/resource_definitions/elb/2012-06-01/resources-1.json
cloudwanderer/aws_interface/resource_definitions/elb/2012-06-01/resources-cw-1.json
cloudwanderer/aws_interface/resource_definitions/elbv2/2015-12-01/resources-1.json
cloudwanderer/aws_interface/resource_definitions/elbv2/2015-12-01/resources-cw-1.json
cloudwanderer/aws_interface/resource_definitions/glacier/2012-06-01/resources-cw-1.json
cloudwanderer/aws_interface/resource_definitions/iam/2010-05-08/resources-1.json
cloudwanderer-0.29.2.dist-info/LICENSE
cloudwanderer-0.29.2.dist-info/METADATA
cloudwanderer-0.29.2.dist-info/WHEEL
cloudwanderer-0.29.2.dist-info/top_level.txt
cloudwanderer-0.29.2.dist-info/RECORD
