Metadata-Version: 2.1
Name: cloudwanderer
Version: 0.29.2
Summary: A Python package which wanders across your AWS account and records resources in multiple databases
Home-page: https://github.com/CloudWanderer-io/CloudWanderer
Author: Sam Martin
Author-email: samjackmartin+cloudwanderer@gmail.com
License: UNKNOWN
Platform: UNKNOWN
Requires-Python: >=3.6.0
License-File: LICENSE
Requires-Dist: boto3
Requires-Dist: jmespath
Requires-Dist: gremlinpython
Requires-Dist: typing-extensions ; python_version < "3.8.0"
